lightweight_charts_esistjosh/__init__.py
lightweight_charts_esistjosh/abstract.py
lightweight_charts_esistjosh/chart.py
lightweight_charts_esistjosh/drawings.py
lightweight_charts_esistjosh/polygon.py
lightweight_charts_esistjosh/table.py
lightweight_charts_esistjosh/toolbox.py
lightweight_charts_esistjosh/topbar.py
lightweight_charts_esistjosh/util.py
lightweight_charts_esistjosh/widgets.py
lightweight_charts_esistjosh/defaults/area.json
lightweight_charts_esistjosh/defaults/bar.json
lightweight_charts_esistjosh/defaults/candlestick.json
lightweight_charts_esistjosh/defaults/chart.json
lightweight_charts_esistjosh/defaults/histogram.json
lightweight_charts_esistjosh/defaults/line.json
lightweight_charts_esistjosh/defaults/ohlc.json
lightweight_charts_esistjosh/defaults/pitchfork.json
lightweight_charts_esistjosh/defaults/trend-trace.json
lightweight_charts_esistjosh/defaults/volume-profile.json
lightweight_charts_esistjosh/js/bundle.js
lightweight_charts_esistjosh/js/lightweight-charts.js
lightweight_charts_esistjosh/scripts/Symbols.json
lightweight_charts_esistjosh/scripts/cache.json
lightweight_charts_esistjosh-3.0.9.dist-info/METADATA
lightweight_charts_esistjosh-3.0.9.dist-info/WHEEL
lightweight_charts_esistjosh-3.0.9.dist-info/top_level.txt
lightweight_charts_esistjosh-3.0.9.dist-info/RECORD
