Metadata-Version: 2.4
Name: lightweight_charts_esistjosh
Version: 3.0.9
Summary: Python framework for TradingView's Lightweight Charts JavaScript library.
Home-page: https://github.com/EsIstJosh/lightweight-charts-python
Author: EsIstJosh
License: MIT/AGPL-3.0
Requires-Python: >=3.8
Requires-Dist: pandas
Requires-Dist: yfinance
Requires-Dist: pywebview>=5.0.5
Dynamic: author
Dynamic: description
Dynamic: description-content-type
Dynamic: home-page
Dynamic: license
Dynamic: requires-dist
Dynamic: requires-python
Dynamic: summary
